<?xml version="1.0" encoding="UTF-8"?>
<!DOCTYPE mapper PUBLIC "-//mybatis.org//DTD Mapper 3.0//EN" "http://mybatis.org/dtd/mybatis-3-mapper.dtd">
<mapper namespace="com.dbExchangeProcess.db.mapper.generated.LabMapper">
  <resultMap id="BaseResultMap" type="com.dbExchangeProcess.db.model.generated.Lab">
    <!--
      WARNING - @mbg.generated
      This element is automatically generated by MyBatis Generator, do not modify.
      This element was generated on Sun Jan 26 13:43:25 JST 2025.
    -->
    <id column="scope" jdbcType="INTEGER" property="scope" />
    <result column="scope_name" jdbcType="VARCHAR" property="scopeName" />
    <result column="sdate" jdbcType="TIMESTAMP" property="sdate" />
    <result column="acess_flg" jdbcType="SMALLINT" property="acessFlg" />
  </resultMap>
  <sql id="Base_Column_List">
    <!--
      WARNING - @mbg.generated
      This element is automatically generated by MyBatis Generator, do not modify.
      This element was generated on Sun Jan 26 13:43:25 JST 2025.
    -->
    scope, scope_name, sdate, acess_flg
  </sql>
  <select id="selectByPrimaryKey" parameterType="java.lang.Integer" resultMap="BaseResultMap">
    <!--
      WARNING - @mbg.generated
      This element is automatically generated by MyBatis Generator, do not modify.
      This element was generated on Sun Jan 26 13:43:25 JST 2025.
    -->
    select 'false' as QUERYID,
    <include refid="Base_Column_List" />
    from lab
    where scope = #{scope,jdbcType=INTEGER}
  </select>
  <delete id="deleteByPrimaryKey" parameterType="java.lang.Integer">
    <!--
      WARNING - @mbg.generated
      This element is automatically generated by MyBatis Generator, do not modify.
      This element was generated on Sun Jan 26 13:43:25 JST 2025.
    -->
    delete from lab
    where scope = #{scope,jdbcType=INTEGER}
  </delete>
  <insert id="insert" parameterType="com.dbExchangeProcess.db.model.generated.Lab">
    <!--
      WARNING - @mbg.generated
      This element is automatically generated by MyBatis Generator, do not modify.
      This element was generated on Sun Jan 26 13:43:25 JST 2025.
    -->
    insert into lab (scope, scope_name, sdate, 
      acess_flg)
    values (#{scope,jdbcType=INTEGER}, #{scopeName,jdbcType=VARCHAR}, #{sdate,jdbcType=TIMESTAMP}, 
      #{acessFlg,jdbcType=SMALLINT})
  </insert>
  <insert id="insertSelective" parameterType="com.dbExchangeProcess.db.model.generated.Lab">
    <!--
      WARNING - @mbg.generated
      This element is automatically generated by MyBatis Generator, do not modify.
      This element was generated on Sun Jan 26 13:43:25 JST 2025.
    -->
    insert into lab
    <trim prefix="(" suffix=")" suffixOverrides=",">
      <if test="scope != null">
        scope,
      </if>
      <if test="scopeName != null">
        scope_name,
      </if>
      <if test="sdate != null">
        sdate,
      </if>
      <if test="acessFlg != null">
        acess_flg,
      </if>
    </trim>
    <trim prefix="values (" suffix=")" suffixOverrides=",">
      <if test="scope != null">
        #{scope,jdbcType=INTEGER},
      </if>
      <if test="scopeName != null">
        #{scopeName,jdbcType=VARCHAR},
      </if>
      <if test="sdate != null">
        #{sdate,jdbcType=TIMESTAMP},
      </if>
      <if test="acessFlg != null">
        #{acessFlg,jdbcType=SMALLINT},
      </if>
    </trim>
  </insert>
  <update id="updateByPrimaryKeySelective" parameterType="com.dbExchangeProcess.db.model.generated.Lab">
    <!--
      WARNING - @mbg.generated
      This element is automatically generated by MyBatis Generator, do not modify.
      This element was generated on Sun Jan 26 13:43:25 JST 2025.
    -->
    update lab
    <set>
      <if test="scopeName != null">
        scope_name = #{scopeName,jdbcType=VARCHAR},
      </if>
      <if test="sdate != null">
        sdate = #{sdate,jdbcType=TIMESTAMP},
      </if>
      <if test="acessFlg != null">
        acess_flg = #{acessFlg,jdbcType=SMALLINT},
      </if>
    </set>
    where scope = #{scope,jdbcType=INTEGER}
  </update>
  <update id="updateByPrimaryKey" parameterType="com.dbExchangeProcess.db.model.generated.Lab">
    <!--
      WARNING - @mbg.generated
      This element is automatically generated by MyBatis Generator, do not modify.
      This element was generated on Sun Jan 26 13:43:25 JST 2025.
    -->
    update lab
    set scope_name = #{scopeName,jdbcType=VARCHAR},
      sdate = #{sdate,jdbcType=TIMESTAMP},
      acess_flg = #{acessFlg,jdbcType=SMALLINT}
    where scope = #{scope,jdbcType=INTEGER}
  </update>
</mapper>